dotenv_linter/__init__.py
dotenv_linter/checker.py
dotenv_linter/cli.py
dotenv_linter/constants.py
dotenv_linter/exceptions.py
dotenv_linter/grammar/__init__.py
dotenv_linter/grammar/fst.py
dotenv_linter/grammar/lexer.py
dotenv_linter/grammar/parser.py
dotenv_linter/grammar/parsetab.py
dotenv_linter/logics/__init__.py
dotenv_linter/logics/report.py
dotenv_linter/logics/text.py
dotenv_linter/version.py
dotenv_linter/violations/__init__.py
dotenv_linter/violations/assigns.py
dotenv_linter/violations/base.py
dotenv_linter/violations/comments.py
dotenv_linter/violations/names.py
dotenv_linter/violations/parsing.py
dotenv_linter/violations/values.py
dotenv_linter/visitors/__init__.py
dotenv_linter/visitors/base.py
dotenv_linter/visitors/fst/__init__.py
dotenv_linter/visitors/fst/assigns.py
dotenv_linter/visitors/fst/comments.py
dotenv_linter/visitors/fst/names.py
dotenv_linter/visitors/fst/values.py
dotenv_linter-0.6.1.dist-info/LICENSE
dotenv_linter-0.6.1.dist-info/METADATA
dotenv_linter-0.6.1.dist-info/WHEEL
dotenv_linter-0.6.1.dist-info/entry_points.txt
dotenv_linter-0.6.1.dist-info/RECORD
