Metadata-Version: 2.3
Name: dotenv-linter
Version: 0.6.1
Summary: Linting dotenv files like a charm!
License: MIT
Keywords: dotenv,linter,wemake.services,code quality
Author: sobolevn
Author-email: mail@sobolevn.me
Requires-Python: >=3.10,<4.0
Classifier: Development Status :: 4 - Beta
Classifier: Environment :: Console
Classifier: Intended Audience :: Developers
Classifier: License :: OSI Approved :: MIT License
Classifier: Operating System :: OS Independent
Classifier: Programming Language :: Python :: 3
Classifier: Programming Language :: Python :: 3.10
Classifier: Programming Language :: Python :: 3.11
Classifier: Programming Language :: Python :: 3.12
Classifier: Programming Language :: Python :: 3.13
Classifier: Topic :: Software Development :: Libraries :: Python Modules
Classifier: Topic :: Software Development :: Quality Assurance
Requires-Dist: attrs
Requires-Dist: click (>=6,<9)
Requires-Dist: click_default_group (>=1.2,<2.0)
Requires-Dist: ply (>=3.11,<4.0)
Requires-Dist: typing_extensions (>=4.0,<5.0)
Project-URL: Homepage, https://dotenv-linter.readthedocs.io
Project-URL: Repository, https://github.com/wemake-services/dotenv-linter
